spotidnldr/__init__.py
spotidnldr/clifi.py
spotidnldr/converter.py
spotidnldr/cover_download.py
spotidnldr/downloader.py
spotidnldr/env_setup.py
spotidnldr/spot.py
spotidnldr/tag_embedder.py
spotidnldr/youtube_search.py
spotidnldr-1.2.0.dist-info/LICENSE
spotidnldr-1.2.0.dist-info/METADATA
spotidnldr-1.2.0.dist-info/WHEEL
spotidnldr-1.2.0.dist-info/entry_points.txt
spotidnldr-1.2.0.dist-info/top_level.txt
spotidnldr-1.2.0.dist-info/RECORD
