Metadata-Version: 2.1
Name: spotidnldr
Version: 1.2.0
Summary: the spotify song downloader
Home-page: https://github.com/raprocks/spotindnldr
Author: Rohit Patil
Author-email: rahulhimesh09@gmail.com
License: UNKNOWN
Download-URL: https://github.com/raprocks/spotidnldr/archive/v1.0.1.tar.gz
Platform: UNKNOWN
Classifier: Natural Language :: English
Classifier: Programming Language :: Python :: 3 :: Only
Classifier: License :: OSI Approved :: GNU General Public License v3 or later (GPLv3+)
Classifier: Operating System :: OS Independent
Requires-Python: >=3.8
Requires-Dist: spotipy
Requires-Dist: pytubeX
Requires-Dist: eyeD3
Requires-Dist: requests
Requires-Dist: click
Requires-Dist: ffmpeg-python
Requires-Dist: ytmusicapi
